EncryptEnv/__init__.py
EncryptEnv/encrypt.py
EncryptEnv-0.0.3.dist-info/METADATA
EncryptEnv-0.0.3.dist-info/WHEEL
EncryptEnv-0.0.3.dist-info/top_level.txt
EncryptEnv-0.0.3.dist-info/RECORD
