Metadata-Version: 2.1
Name: EncryptEnv
Version: 0.0.3
Summary: Encrypt the passwords in the environment variables.
Home-page: http://rd.thinktronltd.com/jeremywang/EncryptEnv
Author: Thinktron
Author-email: jeremywang@thinktronltd.com
License: UNKNOWN
Platform: UNKNOWN
Classifier: Programming Language :: Python :: 3
Classifier: License :: OSI Approved :: MIT License
Classifier: Operating System :: OS Independent
Requires-Dist: cryptography (==2.8)
